db12/__init__.py
db12/__main__.py
db12/benchmark.py
db12/factors.json
DB12-1.0.4.dist-info/LICENSE
DB12-1.0.4.dist-info/METADATA
DB12-1.0.4.dist-info/WHEEL
DB12-1.0.4.dist-info/entry_points.txt
DB12-1.0.4.dist-info/top_level.txt
DB12-1.0.4.dist-info/RECORD
