Metadata-Version: 2.1
Name: DB12
Version: 1.0.4
Summary: DIRAC Benchmark 2012
Home-page: https://github.com/pypa/DIRACGrid/DB12
License: UNKNOWN
Project-URL: Bug Tracker, https://github.com/DIRACGrid/DB12/issues
Platform: UNKNOWN
Classifier: Programming Language :: Python :: 3
Classifier: Programming Language :: Python :: 2.7
Classifier: Operating System :: OS Independent
Requires-Python: >=2.7
License-File: LICENSE
